qiniu_ufop/__init__.py
qiniu_ufop/demo.py
qiniu_ufop/manage.py
qiniu_ufop/response.py
qiniu_ufop/task.py
qiniu_ufop/utils.py
qiniu_ufop/data/.dockerignore
qiniu_ufop/data/Dockerfile
qiniu_ufop/data/demo.py
qiniu_ufop/data/supervisor.conf
qiniu_ufop/management/__init__.py
qiniu_ufop/management/base.py
qiniu_ufop/management/commands/__init__.py
qiniu_ufop/management/commands/createproject.py
qiniu_ufop/management/commands/deploy.py
qiniu_ufop/management/commands/dockerfile.py
qiniu_ufop/management/commands/doraconfig.py
qiniu_ufop/management/commands/process.py
qiniu_ufop/management/commands/runserver.py
qiniu_ufop/management/commands/runworker.py
qiniu_ufop/project/.dockerignore
qiniu_ufop/project/Dockerfile
qiniu_ufop/project/app.py
qiniu_ufop/project/requirements.txt
qiniu_ufop/project/script.sh
qiniu_ufop/project/supervisor.conf
qiniu_ufop/web/__init__.py
qiniu_ufop/web/app.py
qiniu_ufop/web/controllers.py
qiniu_ufop/web/dispatcher.py
qiniu_ufop/web/result.py
tests/__init__.py
qiniu_ufop-0.1.3.dist-info/LICENCE
qiniu_ufop-0.1.3.dist-info/METADATA
qiniu_ufop-0.1.3.dist-info/WHEEL
qiniu_ufop-0.1.3.dist-info/entry_points.txt
qiniu_ufop-0.1.3.dist-info/top_level.txt
qiniu_ufop-0.1.3.dist-info/RECORD
