Metadata-Version: 2.1
Name: qiniu-ufop
Version: 0.1.3
Summary: Qiniu ufop development tool
Home-page: https://github.com/Xavier-Lam/qiniu-ufop
Author: Xavier-Lam
Author-email: Lam.Xavier@hotmail.com
License: UNKNOWN
Keywords: qiniu,ufop,七牛
Platform: UNKNOWN
Classifier: Development Status :: 2 - Pre-Alpha
Classifier: Environment :: Web Environment
Classifier: Intended Audience :: Developers
Classifier: License :: OSI Approved :: MIT License
Classifier: Operating System :: MacOS
Classifier: Operating System :: Microsoft :: Windows
Classifier: Operating System :: POSIX
Classifier: Operating System :: POSIX :: Linux
Classifier: Programming Language :: Python
Classifier: Programming Language :: Python :: 2.7
Classifier: Programming Language :: Python :: 3.4
Classifier: Programming Language :: Python :: 3.5
Classifier: Programming Language :: Python :: 3.6
Classifier: Programming Language :: Python :: 3.7
Classifier: Programming Language :: Python :: Implementation :: CPython
Classifier: Topic :: Internet :: WWW/HTTP
Classifier: Topic :: Internet :: WWW/HTTP :: Dynamic Content
Classifier: Topic :: Software Development :: Libraries
Classifier: Topic :: Software Development :: Libraries :: Application Frameworks
Classifier: Topic :: Software Development :: Libraries :: Python Modules
Classifier: Topic :: Utilities
Requires-Dist: celery (>=4.3.0)
Requires-Dist: PyYAML (>=5.1)
Requires-Dist: redis (>=3.2.0)
Requires-Dist: six (>=1.7.0)
Requires-Dist: tornado (<6.0.0,>=5.1.0)
